stepmix/__init__.py
stepmix/bootstrap.py
stepmix/corrections.py
stepmix/datasets.py
stepmix/stepmix.py
stepmix/utils.py
stepmix/emission/__init__.py
stepmix/emission/build_emission.py
stepmix/emission/categorical.py
stepmix/emission/covariate.py
stepmix/emission/emission.py
stepmix/emission/gaussian.py
stepmix/emission/nested.py
stepmix-2.2.3.dist-info/licenses/LICENSE
stepmix-2.2.3.dist-info/WHEEL
stepmix-2.2.3.dist-info/METADATA
stepmix-2.2.3.dist-info/RECORD
