Metadata-Version: 2.4
Name: stepmix
Version: 2.2.3
Summary: A Python package for stepwise estimation of latent class models with measurement and structural components. The package can also be used to fit mixture models with various observed random variables.
Keywords: clustering,mixtures,lca,em,latent-class-analysis,expectation–maximization
Author-email: Sacha Morin <sacha.morin@mila.quebec>, Robin Legault <robin.legault@umontreal.ca>, Charles-Édouard Giguère <ce.giguere@gmail.com>, Éric Lacourse <eric.lacourse@umontreal.ca>, Roxane de la Sablonnière <roxane.de.la.sablonniere@umontreal.ca>
Requires-Python: >=3.7
Classifier: License :: OSI Approved :: MIT License
Classifier: Programming Language :: Python
Classifier: Programming Language :: Python :: 3
License-File: LICENSE
Requires-Dist: numpy
Requires-Dist: pandas
Requires-Dist: scikit-learn >= 1.0.0, <=1.5.0
Requires-Dist: scipy
Requires-Dist: tqdm
Requires-Dist: black ; extra == "dev"
Requires-Dist: bumpver ; extra == "dev"
Requires-Dist: flit ; extra == "dev"
Requires-Dist: pytest ; extra == "dev"
Requires-Dist: sphinx == 5.3.0 ; extra == "dev"
Requires-Dist: sphinx-rtd-theme == 1.1.1 ; extra == "dev"
Project-URL: Homepage, https://stepmix.readthedocs.io/en/latest/
Provides-Extra: dev
